superslurp/__init__.py
superslurp/__main__.py
superslurp/check_consistency.py
superslurp/parse_date.py
superslurp/parse_items.py
superslurp/parse_store.py
superslurp/parse_totals.py
superslurp/parser.py
superslurp/safe_search.py
superslurp/str_to_float.py
superslurp/superslurp_typing.py
superslurp-0.0.1.dist-info/LICENSE
superslurp-0.0.1.dist-info/METADATA
superslurp-0.0.1.dist-info/WHEEL
superslurp-0.0.1.dist-info/entry_points.txt
superslurp-0.0.1.dist-info/top_level.txt
superslurp-0.0.1.dist-info/RECORD
