Metadata-Version: 2.2
Name: superslurp
Version: 0.0.1
Summary: A parser for SuperU receipts
Author-email: Pierre Sassoulas <pierre.sassoulas@gmail.com>
License: MIT
Keywords: parser,receipt,superu
Classifier: Programming Language :: Python :: 3 :: Only
Classifier: Programming Language :: Python :: 3.12
Classifier: Programming Language :: Python :: 3.13
Requires-Python: >=3.12
License-File: LICENSE
Requires-Dist: pypdf
Provides-Extra: dev
Requires-Dist: pre-commit; extra == "dev"
Requires-Dist: pylint; extra == "dev"
Requires-Dist: pytest-cov; extra == "dev"
